LICENSE
MANIFEST.in
README.md
setup.py
weatherapi/__init__.py
weatherapi/api_helper.py
weatherapi/configuration.py
weatherapi/decorators.py
weatherapi/weatherapi_client.py
weatherapi/controllers/__init__.py
weatherapi/controllers/ap_is_controller.py
weatherapi/controllers/base_controller.py
weatherapi/exceptions/__init__.py
weatherapi/exceptions/api_exception.py
weatherapi/http/__init__.py
weatherapi/http/http_call_back.py
weatherapi/http/http_client.py
weatherapi/http/http_context.py
weatherapi/http/http_method_enum.py
weatherapi/http/http_request.py
weatherapi/http/http_response.py
weatherapi/http/requests_client.py
weatherapi/http/auth/__init__.py
weatherapi/http/auth/custom_query_auth.py
weatherapi/models/__init__.py
weatherapi/models/astro.py
weatherapi/models/astronomy.py
weatherapi/models/astronomy_json_response.py
weatherapi/models/condition.py
weatherapi/models/current.py
weatherapi/models/current_json_response.py
weatherapi/models/day.py
weatherapi/models/forecast.py
weatherapi/models/forecast_1.py
weatherapi/models/forecast_json_response.py
weatherapi/models/forecastday.py
weatherapi/models/forecastday_1.py
weatherapi/models/history_json_response.py
weatherapi/models/hour.py
weatherapi/models/ip_json_response.py
weatherapi/models/location.py
weatherapi/models/search_json_response.py
weatherapi/models/timezone_json_response.py
weatherapi_forked.egg-info/PKG-INFO
weatherapi_forked.egg-info/SOURCES.txt
weatherapi_forked.egg-info/dependency_links.txt
weatherapi_forked.egg-info/requires.txt
weatherapi_forked.egg-info/top_level.txt