Metadata-Version: 2.1
Name: weatherapi-forked
Version: 1.0.0
Summary: Python client library for Weather API
Home-page: https://apimatic.io
Author: APIMatic SDK Generator
Author-email: support@apimatic.io
License: UNKNOWN
Platform: UNKNOWN
License-File: LICENSE
